LICENSE.txt
MANIFEST.in
README.rst
requirements.txt
setup.cfg
setup.py
doc/Makefile
doc/conf.py
doc/index.rst
doc/objects.inv
doc/testenv.1
doc/rst/install.rst
doc/rst/module.rst
doc/rst/refman.rst
doc/rst/tutor.rst
doc/rst/install/extensions.rst
doc/rst/install/ext/testenv.rst
doc/rst/module/extensions.rst
doc/rst/module/ext/testenv/application.rst
doc/rst/module/ext/testenv/main.rst
doc/rst/module/ext/testenv/testenv.rst
doc/rst/module/ext/testenv/fig/01_customer_structure.png
doc/rst/module/ext/testenv/fig/02_contact_address.png
doc/rst/refman/ext/testenv.rst
doc/rst/tutor/extensions.rst
doc/rst/tutor/ext/testenv/testenv.rst
doc/rst/tutor/ext/testenv/tut1_db.rst
doc/rst/tutor/ext/testenv/tut2_rest.rst
doc/rst/tutor/ext/testenv/tut3_soap.rst
doc/rst/tutor/ext/testenv/tut4_gui.rst
etc/hydratk/conf.d/hydratk-ext-testenv.conf
src/hydratk/__init__.py
src/hydratk/extensions/__init__.py
src/hydratk/extensions/testenv/__init__.py
src/hydratk/extensions/testenv/bootstrapper.py
src/hydratk/extensions/testenv/db_handler.py
src/hydratk/extensions/testenv/entities.py
src/hydratk/extensions/testenv/gui_handler.py
src/hydratk/extensions/testenv/rest_handler.py
src/hydratk/extensions/testenv/soap_handler.py
src/hydratk/extensions/testenv/testenv.py
src/hydratk/extensions/testenv/web_server.py
src/hydratk/extensions/testenv/templates/__init__.py
src/hydratk/extensions/testenv/templates/main.html
src/hydratk/extensions/testenv/translation/__init__.py
src/hydratk/extensions/testenv/translation/info.py
src/hydratk/extensions/testenv/translation/cs/__init__.py
src/hydratk/extensions/testenv/translation/cs/help.py
src/hydratk/extensions/testenv/translation/cs/messages.py
src/hydratk/extensions/testenv/translation/en/__init__.py
src/hydratk/extensions/testenv/translation/en/help.py
src/hydratk/extensions/testenv/translation/en/messages.py
src/hydratk_ext_testenv.egg-info/PKG-INFO
src/hydratk_ext_testenv.egg-info/SOURCES.txt
src/hydratk_ext_testenv.egg-info/dependency_links.txt
src/hydratk_ext_testenv.egg-info/entry_points.txt
src/hydratk_ext_testenv.egg-info/not-zip-safe
src/hydratk_ext_testenv.egg-info/top_level.txt
tests/travis.yoda
tests/yoda-tests/hydratk/extensions/testenv/int_gui.jedi
tests/yoda-tests/hydratk/extensions/testenv/int_rest.jedi
